{"cameraMode":{"drawMode":0,"name":"Shaded","section":"Shading Mode"},"sceneLighting":true,"audioPlay":false,"sceneViewState":{"m_AlwaysRefresh":false,"showFog":true,"showSkybox":true,"showFlares":true,"showImageEffects":true,"showParticleSystems":true,"showVisualEffectGraphs":true,"m_FxEnabled":true},"in2DMode":false,"pivot":{"x":508.22796630859377,"y":258.7348327636719,"z":-26.62371826171875},"rotation":{"x":0.05365141108632088,"y":0.002090372610837221,"z":-0.00026295430143363774,"w":0.998750627040863},"size":558.6666259765625,"orthographic":false}